dfply/__init__.py
dfply/base.py
dfply/group.py
dfply/join.py
dfply/reshape.py
dfply/select.py
dfply/set_ops.py
dfply/subset.py
dfply/summarize.py
dfply/summary_functions.py
dfply/transform.py
dfply/vector.py
dfply/window_functions.py
dfply/data/__init__.py
dfply/data/diamonds.csv
dfply-0.3.1.dist-info/DESCRIPTION.rst
dfply-0.3.1.dist-info/METADATA
dfply-0.3.1.dist-info/RECORD
dfply-0.3.1.dist-info/WHEEL
dfply-0.3.1.dist-info/metadata.json
dfply-0.3.1.dist-info/top_level.txt
test/__init__.py
test/test_base.py
test/test_group.py
test/test_join.py
test/test_reshape.py
test/test_select.py
test/test_subset.py
test/test_summarize.py
test/test_summary_functions.py
test/test_transform.py
test/test_vector.py
test/test_window_functions.py
