Metadata-Version: 2.0
Name: dfply
Version: 0.3.1
Summary: dplyr-style piping operations for pandas dataframes
Home-page: https://github.com/kieferk/dfply
Author: Kiefer Katovich
Author-email: kiefer.katovich@gmail.com
License: GNU General Public License v3.0
Keywords: pandas dplyr
Platform: UNKNOWN
Requires-Dist: numpy
Requires-Dist: pandas
